CTRAIN
