Metadata-Version: 2.4
Name: CTRAIN
Version: 0.4.2
Summary: CTRAIN is an unified, modular and comprehensive package for the training and evaluation of certified training techniques.
Author-email: Konstantin Kaulen <kaulen@aim.rwth-aachen.de>
License: MIT License
Keywords: certified training,robustness,machine learning,verification
Requires-Python: >=3.8
License-File: LICENSE
Requires-Dist: torch<2.4.0,>=2
Requires-Dist: torchvision<0.19.0,>=0.12.0
Requires-Dist: numpy<2,>=1.20
Requires-Dist: tqdm>=4
Requires-Dist: smac>=2.3
Requires-Dist: pandas>=2
Requires-Dist: matplotlib>=3
Requires-Dist: seaborn
Requires-Dist: onnxruntime>=1
Requires-Dist: onnxoptimizer
Requires-Dist: skl2onnx
Requires-Dist: appdirs>=1.4
Requires-Dist: graphviz>=0.20.3
Provides-Extra: dev
Requires-Dist: flake8>=7.0; extra == "dev"
Requires-Dist: mkdocs>=1.6; extra == "dev"
Requires-Dist: mkdocstrings>=0.28; extra == "dev"
Requires-Dist: mkdocstrings-python>=1.14; extra == "dev"
Requires-Dist: mkdocs-material>=9.0; extra == "dev"
Requires-Dist: mkdocs-jupyter>=0.25; extra == "dev"
Dynamic: license-file
